LICENSE
LICENSE.txt
README.rst
setup.cfg
setup.py
mynameishh/__init__.py
mynameishh/hh.py
mynameishh.egg-info/PKG-INFO
mynameishh.egg-info/SOURCES.txt
mynameishh.egg-info/dependency_links.txt
mynameishh.egg-info/top_level.txt